setup.cfg
setup.py
proquint/__init__.py
proquint/__main__.py
proquint/proquint.py
proquint/utils.py
proquint.egg-info/PKG-INFO
proquint.egg-info/SOURCES.txt
proquint.egg-info/dependency_links.txt
proquint.egg-info/entry_points.txt
proquint.egg-info/top_level.txt