Metadata-Version: 1.0
Name: proquint
Version: 0.2.1
Summary: Proquints: Identifiers that are Readable, Spellable, and Pronounceable.
Home-page: https://github.com/dsw/proquint
Author: Ruslan Shestopalyuk
Author-email: rushbits@gmail.com
License: UNKNOWN
Platform: UNKNOWN
